[
  {"imagine-halfpenny-think-just": "think"},
  {"dull-debate-brown-bright": "brown"},
  {"custom-feature-tradition-holiday": "tradition"},
  {"puck-duck-hockey-tin": "hockey"},
  {"cloak-dagger-cape-toad": "cape"},
  {"arrive-come-only-now": "come"},
  {"consideration-thought-clement-people": "thought"},
  {"street-newton-road-main": "road"},
  {"observation-look-whores-think": "look"},
  {"shepherd-harvest-sheep-herd": "sheep"},
  {"plank-floor-wood-elf": "floor"},
  {"plants-green-rose-dictionary": "green"},
  {"termite-tent-blueberry-bug": "bug"},
  {"staircase-steps-infertile-foot": "steps"},
  {"numbers-doors-letters-wogs": "letters"},
  {"beast-college-animal-crimes": "animal"},
  {"snort-cigars-anger-pig": "pig"},
  {"deny-lie-fuel-forget": "lie"},
  {"enjoyable-visit-wettest-nice": "nice"},
  {"gladness-holy-reef-joy": "joy"},
  {"signal-glade-inform-train": "train"},
  {"lowest-down-aussie-highest": "down"},
  {"semester-school-undercover-work": "school"},
  {"joining-together-friends-hydrogen": "together"},
  {"boy-son-girl-beats": "son"},
  {"sew-needle-luggage-pants": "needle"},
  {"mechanics-laws-custard-car": "laws"},
  {"christmas-wonder-tree-white": "tree"},
  {"smoke-fire-less-shivers": "fire"},
  {"convent-nun-monastery-atom": "nun"},
  {"headquarters-army-kong-guides": "army"},
  {"prison-caught-bars-inquisitive": "caught"},
  {"infant-baby-little-style": "baby"},
  {"expansion-lesion-detached-contraction": "contraction"},
  {"dictionary-long-words-sweeter": "long"},
  {"mare-ride-weekly-horse": "horse"},
  {"roast-cook-shy-beef": "beef"},
  {"flash-light-news-molecules": "light"},
  {"matchbox-hundreds-matches-tartan": "matches"},
  {"appearance-coming-asking-looks": "looks"},
  {"minister-church-prime-cartoon": "church"},
  {"naked-royce-nude-bum": "nude"},
  {"apartheid-spoke-discussion-black": "black"},
  {"ordinary-dead-usual-dove": "usual"},
  {"budgie-paints-cage-opera": "cage"},
  {"appearance-set-ugly-looks": "looks"},
  {"embrace-kiss-enlarge-fascist": "kiss"},
  {"saving-holding-lullaby-money": "money"},
  {"host-battle-guest-fondle": "guest"},
  {"controls-gadgets-roll-airplane": "airplane"},
  {"spuds-wane-potatoes-dirty": "potatoes"},
  {"bracelet-wrist-keepers-ankle": "wrist"},
  {"luscious-fruit-mm-seaman": "fruit"},
  {"headache-brain-assume-pain": "pain"},
  {"service-duty-station-unbalanced": "duty"},
  {"compartment-expose-train-brain": "train"},
  {"wheel-car-mend-chair": "car"},
  {"fable-story-type-holder": "story"},
  {"cranium-fully-skill-head": "head"},
  {"wicked-impatient-evil-terrible": "evil"},
  {"chance-tail-probability-luck": "probability"},
  {"bluebottle-fly-door-gas": "fly"},
  {"plurals-people-smothering-many": "many"},
  {"memory-remembering-mind-overlay": "remembering"},
  {"essence-bare-smell-pond": "bare"},
  {"charity-places-run-money": "money"},
  {"cuddle-wool-fountain-kiss": "kiss"},
  {"eat-food-stomach-flowers": "food"},
  {"lodge-gob-house-room": "house"},
  {"stocky-fat-infallible-square": "square"},
  {"scaffold-group-high-cod": "group"},
  {"channel-capacity-english-safe": "capacity"},
  {"manners-polite-prune-respectable": "polite"},
  {"patrol-police-officer-conditioner": "police"},
  {"drown-kill-society-water": "water"},
  {"misfit-outcast-gulp-deformity": "outcast"},
  {"sponge-scarlet-bath-suck": "bath"},
  {"abound-plenty-sun-national": "plenty"},
  {"tupperware-plastic-dynamite-rubber": "plastic"},
  {"seafood-appetite-fish-cat": "fish"},
  {"judge-court-monthly-black": "court"},
  {"acrobat-tightrope-lee-gymnast": "gymnast"},
  {"button-hole-loads-boat": "hole"},
  {"hoarse-throat-strain-linen": "throat"},
  {"pay-off-oar-money": "money"},
  {"fore-hind-pawn-aft": "aft"},
  {"mender-buzz-repair-clock": "repair"},
  {"intestines-snake-guts-gland": "guts"},
  {"bigotry-hatred-prejudice-shepherds": "prejudice"},
  {"laziness-sundays-geometry-idle": "sundays"},
  {"soar-lodging-spirit-fly": "fly"},
  {"romantic-nice-love-dixon": "love"},
  {"comrade-friend-army-evening": "friend"},
  {"warts-burning-ugly-alec": "ugly"},
  {"frost-fear-cold-stupid": "cold"},
  {"rationality-bendy-order-reason": "reason"},
  {"attend-lectures-servant-dentist": "lectures"},
  {"reunion-joining-mao-meeting": "meeting"},
  {"growth-cohen-long-big": "long"},
  {"disgrace-shrine-shame-evil": "shame"},
  {"pipe-smoke-holder-mules": "smoke"},
  {"foreword-thine-preface-mended": "preface"},
  {"cause-force-independent-effect": "effect"},
  {"bizarre-marries-bright-strange": "strange"},
  {"jeep-zoology-power-car": "car"},
  {"digit-visual-string-finger": "finger"},
  {"quilt-feathers-dental-blanket": "blanket"},
  {"matrimony-husband-marriage-raspberry": "marriage"},
  {"rocky-pool-mountains-indefinite": "mountains"},
  {"cans-tins-collision-burst": "tins"},
  {"closet-clothes-hide-imply": "clothes"},
  {"keeping-house-together-pastimes": "together"},
  {"surf-ride-beach-eyeball": "beach"},
  {"lend-borrow-owe-bells": "borrow"},
  {"fragrance-cave-smell-sweet": "smell"},
  {"farms-knocks-walls-animals": "animals"},
  {"fade-disappear-wash-memories": "disappear"},
  {"production-unstable-manager-movie": "movie"},
  {"skull-cuddly-mind-head": "head"},
  {"bow-bend-arrow-bitter": "bend"},
  {"crude-ugly-rude-sneak": "ugly"},
  {"dryer-sheets-steep-washer": "sheets"},
  {"restore-replace-store-whosoever": "replace"},
  {"stripe-cat-frankenstein-flag": "flag"},
  {"attitude-bad-idea-test": "bad"},
  {"apex-top-throws-stop": "top"},
  {"cradle-flight-arms-baby": "baby"},
  {"team-football-canned-boat": "football"},
  {"bait-builds-catch-fish": "catch"},
  {"backwards-nous-illiterate-forwards": "forwards"},
  {"producer-movie-typist-writer": "movie"},
  {"rectangle-nip-square-integration": "square"},
  {"tape-queer-scissors-recorder": "scissors"},
  {"once-twice-stormy-rare": "twice"},
  {"division-bell-math-salt": "math"},
  {"month-time-year-tart": "time"},
  {"treasure-zoology-trove-glitters": "trove"},
  {"pal-friend-enemy-skunk": "friend"},
  {"blossom-ring-beauty-flower": "flower"},
  {"faucet-water-drain-exercise": "water"},
  {"quick-overpower-fast-stop": "fast"},
  {"recipe-joyous-food-eat": "food"},
  {"lock-key-close-circus": "key"},
  {"river-forth-floss-stream": "stream"},
  {"russia-dictionary-communist-continent": "communist"},
  {"peanuts-monkeys-opaque-cartoons": "monkeys"},
  {"oboe-instrument-bride-band": "instrument"},
  {"banjo-guitar-string-reel": "guitar"},
  {"ants-spiders-pants-lad": "spiders"},
  {"sandals-leather-shoes-dislike": "shoes"},
  {"bat-ball-hair-checking": "ball"},
  {"lenses-realist-glasses-physics": "glasses"},
  {"benefit-gain-arrives-advantage": "advantage"},
  {"cue-candidate1-candidate2-candidate3": "shoes"},
  {"green-grass-apple-vice": "grass"},
  {"cheeks-white-complain-face": "face"},
  {"fig-newton-dry-gavel": "newton"},
  {"sweat-davidson-perspire-beads": "perspire"},
  {"imprisonment-tail-jail-dennis": "jail"},
  {"jaw-mouth-snow-gum": "mouth"},
  {"crop-tomatoes-wheat-rubbing": "wheat"},
  {"drivers-cars-side-visions": "cars"},
  {"agent-yachts-advertising-secret": "secret"},
  {"dressing-lumps-gown-nude": "gown"},
  {"bawdy-brawl-rowdy-lard": "rowdy"},
  {"commitment-often-faith-marriage": "marriage"},
  {"kick-foot-frightened-hit": "hit"},
  {"fuzzy-eyes-bear-minutes": "bear"},
  {"chuck-boy-throw-theory": "throw"},
  {"meditate-now-circus-think": "think"},
  {"car-target-wheel-king": "wheel"},
  {"been-out-gone-setting": "gone"},
  {"tamer-screw-madam-lion": "lion"},
  {"nothing-wrong-britain-something": "something"},
  {"adore-love-care-waves": "love"},
  {"ewe-lamb-enlist-cry": "lamb"},
  {"spots-dog-blood-oats": "dog"},
  {"kick-grass-ball-shallow": "ball"},
  {"flunk-fail-class-roof": "fail"},
  {"cut-bandage-scissors-nappy": "scissors"},
  {"human-fume-being-issues": "being"},
  {"pearl-foresight-clam-necklace": "necklace"},
  {"sorry-crossword-pardon-oops": "pardon"},
  {"brand-name-spoken-product": "name"},
  {"tinker-copper-smother-tailor": "tailor"},
  {"goblin-tit-elf-dreary": "elf"},
  {"oak-pocketbook-huge-tree": "tree"},
  {"sign-post-abbey-pass": "post"},
  {"sling-stones-clueless-shot": "stones"},
  {"child-shopping-girl-baby": "baby"},
  {"settle-down-back-brat": "down"},
  {"disturb-weaken-annoy-random": "annoy"},
  {"ignorance-daft-bliss-bum": "bliss"},
  {"coast-sea-rocks-argue": "sea"},
  {"plaice-fish-cunt-bottom": "fish"},
  {"pad-flat-restless-false": "false"},
  {"tried-practice-brunette-failed": "failed"},
  {"jaffa-orange-bananas-conductor": "orange"},
  {"prank-joke-fool-rifle": "joke"},
  {"partridge-billy-pheasant-peacock": "pheasant"}
]